[{"name":"Knallhart Durchgenommen #1","description":"Resident Evil 7: Double-Screen-Special","start":"2017-03-12T00:40:00.000","end":"2017-03-12T01:30:00.000","live":false,"premiere":false},{"name":"Knallhart Durchgenommen #2","description":"Resident Evil 7 biohazard mit Nils & Dennis","start":"2017-03-12T01:30:00.000","end":"2017-03-12T02:30:00.000","live":false,"premiere":false},{"name":"Knallhart Durchgenommen #3","description":"Resident Evil 7 biohazard mit Nils & Dennis","start":"2017-03-12T02:30:00.000","end":"2017-03-12T03:35:00.000","live":false,"premiere":false},{"name":"Knallhart Durchgenommen #4","description":"Resident Evil 7 biohazard mit Nils & Dennis","start":"2017-03-12T03:35:00.000","end":"2017-03-12T04:35:00.000","live":false,"premiere":false},{"name":"Knallhart Durchgenommen #5","description":"Resident Evil 7","start":"2017-03-12T04:35:00.000","end":"2017-03-12T05:30:00.000","live":false,"premiere":false},{"name":"Knallhart Durchgenommen #6","description":"Resident Evil 7","start":"2017-03-12T05:30:00.000","end":"2017-03-12T06:35:00.000","live":false,"premiere":false},{"name":"Knallhart Durchgenommen #7","description":"Resident Evil 7","start":"2017-03-12T06:35:00.000","end":"2017-03-12T07:30:00.000","live":false,"premiere":false},{"name":"Knallhart Durchgenommen #8","description":"Resident Evil 7","start":"2017-03-12T07:30:00.000","end":"2017-03-12T08:25:00.000","live":false,"premiere":false},{"name":"Knallhart Durchgenommen #9","description":"Resident Evil 7","start":"2017-03-12T08:25:00.000","end":"2017-03-12T09:20:00.000","live":false,"premiere":false},{"name":"Knallhart Durchgenommen #10","description":"Resident Evil 7","start":"2017-03-12T09:20:00.000","end":"2017-03-12T10:20:00.000","live":false,"premiere":false},{"name":"Knallhart Durchgenommen #11","description":"Resident Evil 7","start":"2017-03-12T10:20:00.000","end":"2017-03-12T11:15:00.000","live":false,"premiere":false},{"name":"New Game Plus #15","description":"Switch Reloaded","start":"2017-03-12T11:15:00.000","end":"2017-03-12T14:00:00.000","live":false,"premiere":false},{"name":"Beanstag #6","description":"The Forest","start":"2017-03-12T14:00:00.000","end":"2017-03-12T16:30:00.000","live":false,"premiere":false},{"name":"RANKED #30","description":"Team Limited: Counter Strike - Global Offensive","start":"2017-03-12T16:30:00.000","end":"2017-03-12T18:00:00.000","live":false,"premiere":false},{"name":"DICED #57","description":"Die Tabletop Show","start":"2017-03-12T18:00:00.000","end":"2017-03-12T18:30:00.000","live":false,"premiere":true},{"name":"Ninotaku Anime News #","description":"Wataaa!","start":"2017-03-12T18:30:00.000","end":"2017-03-12T19:00:00.000","live":false,"premiere":true},{"name":"SRSLY SHOW #8","description":"mit Lars Paulsen","start":"2017-03-12T19:00:00.000","end":"2017-03-12T19:15:00.000","live":false,"premiere":false},{"name":"Game Two #15","description":"Die große Gaming-Show","start":"2017-03-12T19:15:00.000","end":"2017-03-12T21:00:00.000","live":false,"premiere":false},{"name":"Knallhart Durchgenommen #14","description":"Red Dead Edemption","start":"2017-03-12T21:00:00.000","end":"2017-03-12T22:47:00.000","live":false,"premiere":true}]