[{"name":"MoinMoin #554","description":"Die Morning-Show mit Andy","start":"2017-03-23T00:05:00.000","end":"2017-03-23T01:20:00.000","live":false,"premiere":false},{"name":"Game Plus Daily","description":"#112 mit Simon, Gregor, Ilyass, Steffen & Fabian: Shadow Tactics, Game Royale 2 & Little Acre","start":"2017-03-23T01:20:00.000","end":"2017-03-23T03:35:00.000","live":false,"premiere":false},{"name":"Knallhart Durchgenommen #22","description":"Jedi Knight II: Jedi Outcast mit Donnie","start":"2017-03-23T03:35:00.000","end":"2017-03-23T04:35:00.000","live":false,"premiere":false},{"name":"Knallhart Durchgenommen #23","description":"Jedi Knight II: Jedi Outcast mit Donnie","start":"2017-03-23T04:35:00.000","end":"2017-03-23T05:35:00.000","live":false,"premiere":false},{"name":"Knallhart Durchgenommen #8","description":"Red Dead Edemption","start":"2017-03-23T05:35:00.000","end":"2017-03-23T07:40:00.000","live":false,"premiere":false},{"name":"Let’s Play","description":"Simon zockt Pony Island","start":"2017-03-23T07:40:00.000","end":"2017-03-23T08:15:00.000","live":false,"premiere":false},{"name":"Bohn Jour","description":"","start":"2017-03-23T08:15:00.000","end":"2017-03-23T10:30:00.000","live":false,"premiere":false},{"name":"MoinMoin #555","description":"Die Morning-Show mit Anne & Wolf","start":"2017-03-23T10:30:00.000","end":"2017-03-23T11:15:00.000","live":true,"premiere":false},{"name":"Ninotaku Anime News #","description":"Top 10 ZELDA Games","start":"2017-03-23T11:15:00.000","end":"2017-03-23T11:30:00.000","live":false,"premiere":false},{"name":"Last Call #3","description":"Nioh","start":"2017-03-23T11:30:00.000","end":"2017-03-23T12:30:00.000","live":false,"premiere":false},{"name":"Knallhart Durchgenommen #9","description":"The Legend of Zelda: Breath of the Wild","start":"2017-03-23T12:30:00.000","end":"2017-03-23T13:30:00.000","live":false,"premiere":false},{"name":"New Game Plus #20","description":"Toukiden 2, Mobile+ und mehr!","start":"2017-03-23T13:30:00.000","end":"2017-03-23T14:30:00.000","live":false,"premiere":false},{"name":"Nerd Quiz #6","description":"Die Game-Show für Besserwisser","start":"2017-03-23T14:30:00.000","end":"2017-03-23T15:30:00.000","live":false,"premiere":false},{"name":"Knallhart Durchgenommen #2","description":"Mass Effect: Andromeda","start":"2017-03-23T15:30:00.000","end":"2017-03-23T18:00:00.000","live":true,"premiere":false},{"name":"Knallhart Durchgenommen #10","description":"The Legend of Zelda: Breath of the Wild","start":"2017-03-23T18:00:00.000","end":"2017-03-23T19:00:00.000","live":false,"premiere":true},{"name":"Spiele mit Schmerz #6","description":"Das halbe Schmerz-Dutzend ist voll!","start":"2017-03-23T19:00:00.000","end":"2017-03-23T20:00:00.000","live":false,"premiere":true},{"name":"Kino+ #28","description":"Alles rund um Filme mit Daniel und Co.","start":"2017-03-23T20:00:00.000","end":"2017-03-23T22:00:00.000","live":false,"premiere":true},{"name":"Wir müssen reden #23","description":"Live-Call-In mit Gunnar","start":"2017-03-23T22:00:00.000","end":"2017-03-23T23:00:00.000","live":true,"premiere":false},{"name":"Knallhart Durchgenommen #15","description":"Horizon: Zero Dawn","start":"2017-03-23T23:00:00.000","end":"2017-03-24T00:00:00.000","live":false,"premiere":true}]