[{"name":"After Dark","description":"Dead Space 2 mit Simon","start":"2016-09-21T00:00:00.000","end":"2016-09-21T10:30:00.000","live":false,"premiere":true},{"name":"MoinMoin","description":"MoinMoin - Die Morning-Show","start":"2016-09-21T10:30:00.000","end":"2016-09-21T11:20:00.000","live":true,"premiere":false},{"name":"Urknall, Weltall und das Leben #16","description":"","start":"2016-09-21T11:20:00.000","end":"2016-09-21T15:00:00.000","live":false,"premiere":true},{"name":"Let’s Play","description":"Vampire: The Masquerade - Bloodlines mit Bell & Nasti","start":"2016-09-21T15:00:00.000","end":"2016-09-21T17:00:00.000","live":false,"premiere":true},{"name":"Almost Plaily #26","description":"Black Stories","start":"2016-09-21T17:00:00.000","end":"2016-09-21T18:00:00.000","live":false,"premiere":true},{"name":"Game Plus Daily","description":"#73","start":"2016-09-21T18:00:00.000","end":"2016-09-21T20:00:00.000","live":true,"premiere":false},{"name":"RB News","description":"News! Investigativ, Aktuell, Sexy!","start":"2016-09-21T20:00:00.000","end":"2016-09-21T20:04:00.000","live":false,"premiere":true},{"name":"Eric Andre Show","description":"","start":"2016-09-21T20:04:00.000","end":"2016-09-21T20:15:00.000","live":false,"premiere":true},{"name":"Bohn Jour","description":"Bohn Jour","start":"2016-09-21T20:15:00.000","end":"2016-09-21T21:45:00.000","live":true,"premiere":false},{"name":"Weekly Wahnsinn","description":"Weekly Wahnsinn - Partyspiele mit den Beans","start":"2016-09-21T21:45:00.000","end":"2016-09-21T21:55:00.000","live":false,"premiere":true},{"name":"RBTV On Tour","description":"RBTV on Tour auf dem Roskilde Festival","start":"2016-09-21T21:55:00.000","end":"2016-09-21T22:15:00.000","live":false,"premiere":true},{"name":"Let’s Play","description":"Das Fantasy-Abenteuer mit Micha, Micha & Trixi","start":"2016-09-21T22:15:00.000","end":"2016-09-22T00:00:00.000","live":true,"premiere":false}]