[{"name":"RB News","description":"News! Investigativ, Aktuell, Sexy!","start":"2016-10-27T00:30:00.000","end":"2016-10-27T00:40:00.000","live":false,"premiere":false},{"name":"Shocktober2016 #21","description":"mit Gregor und Schröckert","start":"2016-10-27T00:40:00.000","end":"2016-10-27T01:00:00.000","live":false,"premiere":true},{"name":"MoinMoin","description":"Moin Moin - Die Morning-Show mit Simon","start":"2016-10-27T01:00:00.000","end":"2016-10-27T02:20:00.000","live":false,"premiere":false},{"name":"Game Plus Daily","description":"#8 mit Gregor, dem neuen Resident Evil u.v.m.","start":"2016-10-27T02:20:00.000","end":"2016-10-27T04:30:00.000","live":false,"premiere":false},{"name":"Classix","description":"Terranigma mit Gregor","start":"2016-10-27T04:30:00.000","end":"2016-10-27T06:30:00.000","live":false,"premiere":false},{"name":"Almost Daily #251","description":"Festivalgänger und andere gefährliche Typen","start":"2016-10-27T06:30:00.000","end":"2016-10-27T07:35:00.000","live":false,"premiere":false},{"name":"Knallhart Durchgenommen","description":"Gears of War 4 mit Schröck und Simon","start":"2016-10-27T07:35:00.000","end":"2016-10-27T08:30:00.000","live":false,"premiere":false},{"name":"Classix","description":"Terrornigma mit Gregor","start":"2016-10-27T08:30:00.000","end":"2016-10-27T10:30:00.000","live":false,"premiere":false},{"name":"MoinMoin","description":"Moin Moin - Die Morning-Show mit Lars","start":"2016-10-27T10:30:00.000","end":"2016-10-27T11:20:00.000","live":true,"premiere":false},{"name":"Almost Daily #252","description":"Hallo YouTube!","start":"2016-10-27T11:20:00.000","end":"2016-10-27T12:10:00.000","live":false,"premiere":false},{"name":"Heimwerkerking #28","description":"","start":"2016-10-27T12:10:00.000","end":"2016-10-27T12:30:00.000","live":false,"premiere":false},{"name":"Game Plus Daily","description":"#92 mit Nils, Alwin & Gunnar: Gwent & Landwirtschafts-Simulator 17","start":"2016-10-27T12:30:00.000","end":"2016-10-27T14:30:00.000","live":false,"premiere":false},{"name":"German Treasure Hunter #10","description":"","start":"2016-10-27T14:30:00.000","end":"2016-10-27T15:00:00.000","live":false,"premiere":false},{"name":"Let’s Play","description":"Fallout 4: Nuka-World mit Nuka-Nils","start":"2016-10-27T15:00:00.000","end":"2016-10-27T17:00:00.000","live":true,"premiere":false},{"name":"Buchklub #","description":"Der zweite Teil mit Markus Heitz","start":"2016-10-27T17:00:00.000","end":"2016-10-27T17:30:00.000","live":false,"premiere":true},{"name":"Social Eating","description":"Social Eating mit Etienne","start":"2016-10-27T17:30:00.000","end":"2016-10-27T18:00:00.000","live":true,"premiere":false},{"name":"Game Plus Daily","description":"#93 mit Simon, Dennis & Ilyass: Dark Souls III, Overwatch & Pokémon","start":"2016-10-27T18:00:00.000","end":"2016-10-27T20:00:00.000","live":true,"premiere":false},{"name":"RB News","description":"News! Investigativ, Aktuell, Sexy!","start":"2016-10-27T20:00:00.000","end":"2016-10-27T20:15:00.000","live":false,"premiere":true},{"name":"Kino+","description":"kino+ mit Daniel","start":"2016-10-27T20:15:00.000","end":"2016-10-27T22:30:00.000","live":false,"premiere":true},{"name":"Let’s Play","description":"Titanfall 2 mit Titanimon","start":"2016-10-27T22:30:00.000","end":"2016-10-28T00:02:00.000","live":true,"premiere":false}]