[{"name":"Game Plus Daily","description":"Host: Micha | Thema u.a. Dating-Games","start":"2016-06-27T02:00:00.000","end":"2016-06-27T04:00:00.000","live":false,"premiere":false},{"name":"Game Plus Daily","description":"Host: Gregor | Thema u.a. Trials Of The Blood Dragon","start":"2016-06-27T04:00:00.000","end":"2016-06-27T06:00:00.000","live":false,"premiere":false},{"name":"Almost Daily #132","description":"Wer Bin Ich","start":"2016-06-27T06:00:00.000","end":"2016-06-27T07:00:00.000","live":false,"premiere":false},{"name":"Game Plus Daily","description":"Host: Etienne | Mods: Jan & Denzel","start":"2016-06-27T07:00:00.000","end":"2016-06-27T09:00:00.000","live":false,"premiere":false},{"name":"Let’s Play","description":"Rocketbirds 2 mit Sofia & Lars","start":"2016-06-27T09:00:00.000","end":"2016-06-27T10:30:00.000","live":false,"premiere":false},{"name":"MoinMoin","description":"Die Morning-Show mit Sofia & Krogmann - Roskilde Special","start":"2016-06-27T10:30:00.000","end":"2016-06-27T11:15:00.000","live":true,"premiere":false},{"name":"Almost Daily #133","description":"Gaming","start":"2016-06-27T11:15:00.000","end":"2016-06-27T12:15:00.000","live":false,"premiere":false},{"name":"Let’s Play","description":"Simon zockt Pony Island","start":"2016-06-27T12:15:00.000","end":"2016-06-27T12:50:00.000","live":false,"premiere":false},{"name":"Let’s Play","description":"Micha & Krogi zocken Gothic II","start":"2016-06-27T12:50:00.000","end":"2016-06-27T15:00:00.000","live":false,"premiere":false},{"name":"Almost Plaily #16","description":"Privacy","start":"2016-06-27T15:00:00.000","end":"2016-06-27T16:00:00.000","live":false,"premiere":false},{"name":"Buchklub #34","description":"","start":"2016-06-27T16:00:00.000","end":"2016-06-27T16:30:00.000","live":false,"premiere":false},{"name":"Panelz","description":"mit dem Blitz & Tim","start":"2016-06-27T16:30:00.000","end":"2016-06-27T17:10:00.000","live":false,"premiere":false},{"name":"Die Grillshow #39","description":"","start":"2016-06-27T17:10:00.000","end":"2016-06-27T17:30:00.000","live":false,"premiere":false},{"name":"DICED #39","description":"","start":"2016-06-27T17:30:00.000","end":"2016-06-27T18:00:00.000","live":false,"premiere":false},{"name":"Game Plus Daily","description":"Mit Etienne, Colin, Dennis, Pac-Man 256 & Odin Sphere","start":"2016-06-27T18:00:00.000","end":"2016-06-27T20:00:00.000","live":true,"premiere":false},{"name":"RB News","description":"News! Investigativ, Aktuell, Sexy!","start":"2016-06-27T20:00:00.000","end":"2016-06-27T20:10:00.000","live":false,"premiere":true},{"name":"Fragen an Käpt'n Schwandt #25","description":"","start":"2016-06-27T20:10:00.000","end":"2016-06-27T20:15:00.000","live":false,"premiere":true},{"name":"After Dark","description":"Dead Space mit Simon","start":"2016-06-27T20:15:00.000","end":"2016-06-27T21:30:00.000","live":false,"premiere":true},{"name":"Let’s Play","description":"Vampire: The Masquerade – Bloodlines mit Bell & Nasti","start":"2016-06-27T21:30:00.000","end":"2016-06-27T22:30:00.000","live":true,"premiere":false},{"name":"Wir müssen reden","description":"Hobbies","start":"2016-06-27T22:30:00.000","end":"2016-06-28T00:09:00.000","live":false,"premiere":false}]