[{"name":"MoinMoin","description":"Die Morning-Show","start":"2016-08-24T10:30:00.000","end":"2016-08-24T11:20:00.000","live":true,"premiere":false},{"name":"Almost Daily #190","description":"Depressionen & Ängste","start":"2016-08-24T11:20:00.000","end":"2016-08-24T13:30:00.000","live":false,"premiere":false},{"name":"Game Plus Daily","description":"#56","start":"2016-08-24T13:30:00.000","end":"2016-08-24T17:00:00.000","live":false,"premiere":false},{"name":"Almost Plaily #","description":"","start":"2016-08-24T17:00:00.000","end":"2016-08-24T18:00:00.000","live":false,"premiere":true},{"name":"Game Plus Daily","description":"#57","start":"2016-08-24T18:00:00.000","end":"2016-08-24T20:00:00.000","live":true,"premiere":false},{"name":"RB News","description":"News! Investigativ, Aktuell, Sexy!","start":"2016-08-24T20:00:00.000","end":"2016-08-24T20:15:00.000","live":false,"premiere":true},{"name":"Bohn Jour","description":"","start":"2016-08-24T20:15:00.000","end":"2016-08-24T21:45:00.000","live":true,"premiere":false},{"name":"Weekly Wahnsinn","description":"Partyspiele mit den Beans","start":"2016-08-24T21:45:00.000","end":"2016-08-24T22:00:00.000","live":false,"premiere":true},{"name":"Let’s Play","description":"Micha, Micha und Trixi treibens wild in Gothic II","start":"2016-08-24T22:00:00.000","end":"2016-08-25T00:00:00.000","live":true,"premiere":false}]